jdxpy/__init__.py
jdxpy/core.py
jdxpy-0.1.2.dist-info/licenses/LICENSE
jdxpy-0.1.2.dist-info/METADATA
jdxpy-0.1.2.dist-info/WHEEL
jdxpy-0.1.2.dist-info/top_level.txt
jdxpy-0.1.2.dist-info/RECORD
