Metadata-Version: 2.4
Name: jdxpy
Version: 0.1.2
Summary: A Python library for development experience enhancement
Author-email: DxPy Developers <jdxpy-developers@sugarperson.net>
Maintainer-email: DxPy Developers <jdxpy-developers@sugarperson.net>
License: Apache-2.0
Project-URL: Homepage, https://github.com/sugarperson-net/jdxpy
Project-URL: Repository, https://github.com/sugarperson-net/jdxpy
Project-URL: Documentation, https://jdxpy.readthedocs.io
Project-URL: Changelog, https://github.com/sugarperson-net/jdxpy/blob/main/CHANGELOG.md
Project-URL: Bug Tracker, https://github.com/sugarperson-net/jdxpy/issues
Keywords: dx,development,experience,tools
Classifier: Development Status :: 3 - Alpha
Classifier: Intended Audience :: Developers
Classifier: License :: OSI Approved :: Apache Software License
Classifier: Programming Language :: Python :: 3
Classifier: Programming Language :: Python :: 3.11
Classifier: Programming Language :: Python :: 3.12
Classifier: Programming Language :: Python :: 3.13
Classifier: Operating System :: OS Independent
Classifier: Topic :: Software Development :: Libraries :: Python Modules
Requires-Python: >=3.11
License-File: LICENSE
Provides-Extra: dev
Requires-Dist: pytest>=7.0; extra == "dev"
Requires-Dist: pytest-cov>=4.0; extra == "dev"
Requires-Dist: black>=23.0; extra == "dev"
Requires-Dist: flake8>=6.0; extra == "dev"
Requires-Dist: mypy>=1.0; extra == "dev"
Requires-Dist: pre-commit>=3.0; extra == "dev"
Provides-Extra: docs
Requires-Dist: sphinx>=6.0; extra == "docs"
Requires-Dist: sphinx-rtd-theme>=1.0; extra == "docs"
Dynamic: license-file
